edc_reports/__init__.py
edc_reports/apps.py
edc_reports/crf_pdf_report.py
edc_reports/crfs_to_pdf.py
edc_reports/numbered_canvas.py
edc_reports/report.py
edc_reports/urls.py
edc_reports/static/edc_reports/clinicedc_logo.jpg
edc_reports/tests/__init__.py
edc_reports/tests/my_report.py
edc_reports/tests/test_report.py
edc_reports-0.3.8.dist-info/LICENSE
edc_reports-0.3.8.dist-info/METADATA
edc_reports-0.3.8.dist-info/WHEEL
edc_reports-0.3.8.dist-info/top_level.txt
edc_reports-0.3.8.dist-info/RECORD
